voxsql/__init__.py
voxsql/_version.py
voxsql/binders.py
voxsql/cli.py
voxsql/framer.py
voxsql/parser.py
voxsql/regexes.py
voxsql/translators.py
voxsql/utils.py
voxsql-0.1.3.dist-info/LICENSE
voxsql-0.1.3.dist-info/METADATA
voxsql-0.1.3.dist-info/WHEEL
voxsql-0.1.3.dist-info/entry_points.txt
voxsql-0.1.3.dist-info/top_level.txt
voxsql-0.1.3.dist-info/RECORD
