Metadata-Version: 2.1
Name: voxsql
Version: 0.1.3
Summary: Generate application artifacts from documented SQL code
Home-page: https://github.com/ccortezia/voxsql/
Author: Cristiano Cortezia
Author-email: cristiano.cortezia@gmail.com
License: MIT
Platform: UNKNOWN
Classifier: License :: OSI Approved :: MIT License
Classifier: Programming Language :: Python :: 3
Classifier: Programming Language :: Python :: 3.7
Requires-Dist: Click
